Metadata-Version: 1.0
Name: tro
Version: 0.1
Summary: Best Dog
Home-page: https://github.com/fxie97/python-packaging-template
Author: gerardnavarro22
Author-email: gerard.navarro22@gmail.com
License: MIT
Platform: UNKNOWN
